smfc/__init__.py
smfc/cmd.py
smfc/constzone.py
smfc/cpuzone.py
smfc/fancontroller.py
smfc/gpuzone.py
smfc/hdzone.py
smfc/ipmi.py
smfc/log.py
smfc/service.py
smfc-4.1.1.dist-info/licenses/LICENSE
smfc-4.1.1.dist-info/METADATA
smfc-4.1.1.dist-info/WHEEL
smfc-4.1.1.dist-info/entry_points.txt
smfc-4.1.1.dist-info/top_level.txt
smfc-4.1.1.dist-info/RECORD
