Metadata-Version: 2.4
Name: smfc
Version: 4.1.1
Summary: Super Micro Fan Control for Linux
Author-email: Peter Sulyok <peter@sulyok.net>
License-Expression: GPL-3.0-only
Project-URL: Homepage, https://github.com/petersulyok/smfc
Project-URL: Changelog, https://github.com/petersulyok/smfc/blob/main/CHANGELOG.md
Project-URL: Issues, https://github.com/petersulyok/smfc/issues
Keywords: supermicro,linux,daemon,fancontrol
Classifier: Programming Language :: Python :: 3.9
Classifier: Programming Language :: Python :: 3.10
Classifier: Programming Language :: Python :: 3.11
Classifier: Programming Language :: Python :: 3.12
Classifier: Programming Language :: Python :: 3.13
Classifier: Operating System :: POSIX :: Linux
Classifier: Topic :: System :: Hardware
Classifier: Development Status :: 5 - Production/Stable
Requires-Python: <4,>=3.9
License-File: LICENSE
Requires-Dist: pyudev
Dynamic: license-file
